r503/__init__.py
r503/r503.py
r503-0.0.1.dist-info/METADATA
r503-0.0.1.dist-info/WHEEL
r503-0.0.1.dist-info/top_level.txt
r503-0.0.1.dist-info/RECORD
