Metadata-Version: 2.1
Name: r503
Version: 0.0.1
Summary: Fingerprint reader R503
Author: RoshanCS
Author-email: <roshan.cs790@gmail.com>
Keywords: python,fingerprint,security,grow,r503,password
Classifier: Development Status :: 1 - Planning
Classifier: Intended Audience :: Developers
Classifier: Programming Language :: Python :: 3
Classifier: Operating System :: Unix
Classifier: Operating System :: MacOS :: MacOS X
Classifier: Operating System :: Microsoft :: Windows
Requires-Dist: pyserial
